[
    {
        "date": "07/09/24",
        "fixtype": "L",
        "time": "10:30",
        "home_team": "Rockleaze Rangers U15 Reds",
        "away_team": "Port of Bristol U15",
        "competition": "U15B",
        "score": "1 - 6"
    },
    {
        "date": "07/09/24",
        "fixtype": "Cup",
        "time": "10:30",
        "home_team": "Cotham Tigers U15",
        "away_team": "Rockleaze Rangers U15 Blacks",
        "competition": "U15s Plate_2024 - 2025",
        "score": "3 - 2"
    },
    {
        "date": "14/09/24",
        "fixtype": "Cup",
        "time": "10:30",
        "home_team": "Rockleaze Rangers U15 Blacks",
        "away_team": "Bradley Stoke U15 Gold",
        "competition": "U15s Plate_2024 - 2025",
        "score": "3 - 6"
    },
    {
        "date": "14/09/24",
        "fixtype": "Cup",
        "time": "10:30",
        "home_team": "Rockleaze Rangers U15 Reds",
        "away_team": "Tyrone Mings Academy U15 Avalanche",
        "competition": "U15s Cup_2024 - 2025",
        "score": "2 - 2 \r\n\t\t\t\t\t\t\t\t\t\t\r\n\t\t\t\t\t\t\t\t\t\t\t\n(HT 1-1)"
    },
    {
        "date": "21/09/24",
        "fixtype": "Cup",
        "time": "10:30",
        "home_team": "Bishop Road Buccaneers U15",
        "away_team": "Rockleaze Rangers U15 Reds",
        "competition": "U15s Cup_2024 - 2025",
        "score": "3 - 2 \r\n\t\t\t\t\t\t\t\t\t\t\r\n\t\t\t\t\t\t\t\t\t\t\t\n(HT 0-0)"
    },
    {
        "date": "21/09/24",
        "fixtype": "Cup",
        "time": "10:30",
        "home_team": "Portishead Town U15 Sparks",
        "away_team": "Rockleaze Rangers U15 Blacks",
        "competition": "U15s Plate_2024 - 2025",
        "score": "7 - 1 \r\n\t\t\t\t\t\t\t\t\t\t\r\n\t\t\t\t\t\t\t\t\t\t\t\n(HT 5-0)"
    },
    {
        "date": "28/09/24",
        "fixtype": "Cup",
        "time": "10:30",
        "home_team": "Rockleaze Rangers U15 Blacks",
        "away_team": "FC United U15",
        "competition": "U15s Plate_2024 - 2025",
        "score": "7 - 1"
    },
    {
        "date": "28/09/24",
        "fixtype": "Cup",
        "time": "10:30",
        "home_team": "Rockleaze Rangers U15 Reds",
        "away_team": "Port of Bristol U15",
        "competition": "U15s Cup_2024 - 2025",
        "score": "5 - 9"
    },
    {
        "date": "05/10/24",
        "fixtype": "L",
        "time": "10:30",
        "home_team": "Rockleaze Rangers U15 Reds",
        "away_team": "Frampton Rangers U15",
        "competition": "U15B",
        "score": "3 - 4 \r\n\t\t\t\t\t\t\t\t\t\t\r\n\t\t\t\t\t\t\t\t\t\t\t\n(HT 1-2)"
    },
    {
        "date": "05/10/24",
        "fixtype": "Cup",
        "time": "10:30",
        "home_team": "Rockleaze Rangers U15 Blacks",
        "away_team": "Shirehampton Colts U15",
        "competition": "U15s Plate_2024 - 2025",
        "score": "Home Walkover\r\n\t\t\t\t\t\t\t\t\t\t\r\n\t\t\t\t\t\t\t\t\t\tH - W"
    },
    {
        "date": "19/10/24",
        "fixtype": "Cup",
        "time": "10:30",
        "home_team": "Yatton Athletic U15 Rangers",
        "away_team": "Rockleaze Rangers U15 Blacks",
        "competition": "U15s Plate_2024 - 2025",
        "score": "4 - 0"
    },
    {
        "date": "09/11/24",
        "fixtype": "L",
        "time": "10:30",
        "home_team": "Rockleaze Rangers U15 Reds",
        "away_team": "Portishead Town U15 Sparks",
        "competition": "U15B",
        "score": "4 - 1 \r\n\t\t\t\t\t\t\t\t\t\t\r\n\t\t\t\t\t\t\t\t\t\t\t\n(HT 0-1)"
    },
    {
        "date": "09/11/24",
        "fixtype": "L",
        "time": "10:30",
        "home_team": "FC United U15",
        "away_team": "Rockleaze Rangers U15 Blacks",
        "competition": "U15C",
        "score": "3 - 4 \r\n\t\t\t\t\t\t\t\t\t\t\r\n\t\t\t\t\t\t\t\t\t\t\t\n(HT 2-3)"
    },
    {
        "date": "12/11/24",
        "fixtype": "L",
        "time": "18:30",
        "home_team": "Fry Club Juniors U15",
        "away_team": "Rockleaze Rangers U15 Reds",
        "competition": "U15B",
        "score": "2 - 8 \r\n\t\t\t\t\t\t\t\t\t\t\r\n\t\t\t\t\t\t\t\t\t\t\t\n(HT 0-3)"
    },
    {
        "date": "16/11/24",
        "fixtype": "L",
        "time": "10:30",
        "home_team": "Port of Bristol U15",
        "away_team": "Rockleaze Rangers U15 Reds",
        "competition": "U15B",
        "score": "8 - 1"
    },
    {
        "date": "16/11/24",
        "fixtype": "L",
        "time": "10:30",
        "home_team": "Rockleaze Rangers U15 Blacks",
        "away_team": "Bradley Stoke U15 Gold",
        "competition": "U15C",
        "score": "9 - 2"
    },
    {
        "date": "23/11/24",
        "fixtype": "L",
        "time": "10:30",
        "home_team": "Rockleaze Rangers U15 Reds",
        "away_team": "Backwell Athletic Junior U15",
        "competition": "U15B",
        "score": "2 - 1"
    },
    {
        "date": "23/11/24",
        "fixtype": "L",
        "time": "10:30",
        "home_team": "Shirehampton Colts U15",
        "away_team": "Rockleaze Rangers U15 Blacks",
        "competition": "U15C",
        "score": "1 - 5"
    },
    {
        "date": "30/11/24",
        "fixtype": "L",
        "time": "10:30",
        "home_team": "Olveston United U15",
        "away_team": "Rockleaze Rangers U15 Reds",
        "competition": "U15B",
        "score": "3 - 1"
    },
    {
        "date": "30/11/24",
        "fixtype": "L",
        "time": "10:30",
        "home_team": "Rockleaze Rangers U15 Blacks",
        "away_team": "Cotham Tigers U15",
        "competition": "U15C",
        "score": "3 - 3 \r\n\t\t\t\t\t\t\t\t\t\t\r\n\t\t\t\t\t\t\t\t\t\t\t\n(HT 0-3)"
    },
    {
        "date": "14/12/24",
        "fixtype": "L",
        "time": "10:30",
        "home_team": "Frampton Rangers U15",
        "away_team": "Rockleaze Rangers U15 Reds",
        "competition": "U15B",
        "score": "7 - 3 \r\n\t\t\t\t\t\t\t\t\t\t\r\n\t\t\t\t\t\t\t\t\t\t\t\n(HT 3-1)"
    },
    {
        "date": "11/01/25",
        "fixtype": "L",
        "time": "10:30",
        "home_team": "Rockleaze Rangers U15 Reds",
        "away_team": "Fry Club Juniors U15",
        "competition": "U15B",
        "score": "3 - 1 \r\n\t\t\t\t\t\t\t\t\t\t\r\n\t\t\t\t\t\t\t\t\t\t\t\n(HT 0-0)"
    },
    {
        "date": "11/01/25",
        "fixtype": "L",
        "time": "10:30",
        "home_team": "Rockleaze Rangers U15 Blacks",
        "away_team": "Yatton Athletic U15 Rangers",
        "competition": "U15C",
        "score": "0 - 4"
    },
    {
        "date": "18/01/25",
        "fixtype": "L",
        "time": "10:30",
        "home_team": "Portishead Town U15 Sparks",
        "away_team": "Rockleaze Rangers U15 Reds",
        "competition": "U15B",
        "score": "0 - 2"
    },
    {
        "date": "18/01/25",
        "fixtype": "L",
        "time": "10:30",
        "home_team": "Rockleaze Rangers U15 Blacks",
        "away_team": "FC United U15",
        "competition": "U15C",
        "score": "8 - 3"
    },
    {
        "date": "25/01/25",
        "fixtype": "L",
        "time": "10:30",
        "home_team": "Backwell Athletic Junior U15",
        "away_team": "Rockleaze Rangers U15 Reds",
        "competition": "U15B",
        "score": "3 - 3"
    },
    {
        "date": "25/01/25",
        "fixtype": "L",
        "time": "10:30",
        "home_team": "Bradley Stoke U15 Gold",
        "away_team": "Rockleaze Rangers U15 Blacks",
        "competition": "U15C",
        "score": "6 - 0"
    },
    {
        "date": "01/02/25",
        "fixtype": "L",
        "time": "10:30",
        "home_team": "Rockleaze Rangers U15 Reds",
        "away_team": "Olveston United U15",
        "competition": "U15B",
        "score": "2 - 4"
    },
    {
        "date": "01/02/25",
        "fixtype": "L",
        "time": "10:30",
        "home_team": "Rockleaze Rangers U15 Blacks",
        "away_team": "Shirehampton Colts U15",
        "competition": "U15C",
        "score": "6 - 1"
    },
    {
        "date": "08/02/25",
        "fixtype": "L",
        "time": "10:30",
        "home_team": "Golden Hill Sonics U15",
        "away_team": "Rockleaze Rangers U15 Reds",
        "competition": "U15B",
        "score": "3 - 1"
    },
    {
        "date": "08/02/25",
        "fixtype": "L",
        "time": "10:30",
        "home_team": "Cotham Tigers U15",
        "away_team": "Rockleaze Rangers U15 Blacks",
        "competition": "U15C",
        "score": "3 - 3 \r\n\t\t\t\t\t\t\t\t\t\t\r\n\t\t\t\t\t\t\t\t\t\t\t\n(HT 3-3)"
    },
    {
        "date": "01/03/25",
        "fixtype": "L",
        "time": "10:30",
        "home_team": "Rockleaze Rangers U15 Blacks",
        "away_team": "Westbury Park Foxes U15",
        "competition": "U15C",
        "score": "1 - 2"
    },
    {
        "date": "15/03/25",
        "fixtype": "L",
        "time": "10:30",
        "home_team": "Yatton Athletic U15 Rangers",
        "away_team": "Rockleaze Rangers U15 Blacks",
        "competition": "U15C",
        "score": "0 - 1 \r\n\t\t\t\t\t\t\t\t\t\t\r\n\t\t\t\t\t\t\t\t\t\t\t\n(HT 0-1)"
    },
    {
        "date": "22/03/25",
        "fixtype": "L",
        "time": "10:30",
        "home_team": "Rockleaze Rangers U15 Reds",
        "away_team": "Golden Hill Sonics U15",
        "competition": "U15B",
        "notes": ""
    },
    {
        "date": "22/03/25",
        "fixtype": "L",
        "time": "10:30",
        "home_team": "Westbury Park Foxes U15",
        "away_team": "Rockleaze Rangers U15 Blacks",
        "competition": "U15C",
        "notes": ""
    }
]